{
  "db_name": "SQLite",
  "query": "SELECT * FROM rides WHERE date LIKE ? ORDER BY date ASC",
  "describe": {
    "columns": [
      {
        "name": "id",
        "ordinal": 0,
        "type_info": "Int64"
      },
      {
        "name": "date",
        "ordinal": 1,
        "type_info": "Text"
      },
      {
        "name": "distance",
        "ordinal": 2,
        "type_info": "Float"
      },
      {
        "name": "description",
        "ordinal": 3,
        "type_info": "Text"
      }
    ],
    "parameters": {
      "Right": 1
    },
    "nullable": [
      false,
      false,
      false,
      true
    ]
  },
  "hash": "3d946362a3cfaf27203e288da3b0a6762b58588d344ea183bbc855b3e4ddef04"
}
